{
  "72458495": [
    {
      "project_id": "72458495",
      "id": "3faffc01082bbe6d844f17d194f21e40fa8812fa",
      "short_id": "3faffc01",
      "created_at": "2025-08-06T11:29:26.000+01:00",
      "parent_ids": [
        "65d0d93042389918e29508ea4c4bc280c235bee3"
      ],
      "title": "apikey2 test",
      "message": "apikey2 test\n",
      "author_name": "anasakhssas",
      "author_email": "anasakhssas357@gmail.com",
      "authored_date": "2025-08-06T11:29:26.000+01:00",
      "committer_name": "anasakhssas",
      "committer_email": "anasakhssas357@gmail.com",
      "committed_date": "2025-08-06T11:29:26.000+01:00",
      "trailers": {},
      "extended_trailers": {},
      "web_url": "https://gitlab.com/stagepfa/test_1046_0806/-/commit/3faffc01082bbe6d844f17d194f21e40fa8812fa"
    },
    {
      "project_id": "72458495",
      "id": "65d0d93042389918e29508ea4c4bc280c235bee3",
      "short_id": "65d0d930",
      "created_at": "2025-08-06T11:26:04.000+01:00",
      "parent_ids": [
        "7e9a9410ad8abcc9308c39026fb70746a22e74ba"
      ],
      "title": "apikey test",
      "message": "apikey test\n",
      "author_name": "anasakhssas",
      "author_email": "anasakhssas357@gmail.com",
      "authored_date": "2025-08-06T11:26:04.000+01:00",
      "committer_name": "anasakhssas",
      "committer_email": "anasakhssas357@gmail.com",
      "committed_date": "2025-08-06T11:26:04.000+01:00",
      "trailers": {},
      "extended_trailers": {},
      "web_url": "https://gitlab.com/stagepfa/test_1046_0806/-/commit/65d0d93042389918e29508ea4c4bc280c235bee3"
    },
    {
      "project_id": "72458495",
      "id": "7e9a9410ad8abcc9308c39026fb70746a22e74ba",
      "short_id": "7e9a9410",
      "created_at": "2025-08-06T10:21:37.000+00:00",
      "parent_ids": [
        "abd97b66484b82cfbc195f1a29637c355f3e7ab0"
      ],
      "title": "Edit .gitlab-ci.yml",
      "message": "Edit .gitlab-ci.yml",
      "author_name": "Anas Akhssas",
      "author_email": "anasakhssas1@gmail.com",
      "authored_date": "2025-08-06T10:21:37.000+00:00",
      "committer_name": "Anas Akhssas",
      "committer_email": "anasakhssas1@gmail.com",
      "committed_date": "2025-08-06T10:21:37.000+00:00",
      "trailers": {},
      "extended_trailers": {},
      "web_url": "https://gitlab.com/stagepfa/test_1046_0806/-/commit/7e9a9410ad8abcc9308c39026fb70746a22e74ba"
    },
    {
      "project_id": "72458495",
      "id": "abd97b66484b82cfbc195f1a29637c355f3e7ab0",
      "short_id": "abd97b66",
      "created_at": "2025-08-06T09:49:47.000+00:00",
      "parent_ids": [
        "b5d9293a34705645fba661dba48f1d0ff479ec7c"
      ],
      "title": "hello world",
      "message": "hello world",
      "author_name": "Anas Akhssas",
      "author_email": "anasakhssas1@gmail.com",
      "authored_date": "2025-08-06T09:49:47.000+00:00",
      "committer_name": "Anas Akhssas",
      "committer_email": "anasakhssas1@gmail.com",
      "committed_date": "2025-08-06T09:49:47.000+00:00",
      "trailers": {},
      "extended_trailers": {},
      "web_url": "https://gitlab.com/stagepfa/test_1046_0806/-/commit/abd97b66484b82cfbc195f1a29637c355f3e7ab0"
    },
    {
      "project_id": "72458495",
      "id": "b5d9293a34705645fba661dba48f1d0ff479ec7c",
      "short_id": "b5d9293a",
      "created_at": "2025-08-06T09:47:57.000+00:00",
      "parent_ids": [
        "53c27254c142dd7ab7a591da9e6ca1d15ca7118c"
      ],
      "title": "Add new file",
      "message": "Add new file",
      "author_name": "Anas Akhssas",
      "author_email": "anasakhssas1@gmail.com",
      "authored_date": "2025-08-06T09:47:57.000+00:00",
      "committer_name": "Anas Akhssas",
      "committer_email": "anasakhssas1@gmail.com",
      "committed_date": "2025-08-06T09:47:57.000+00:00",
      "trailers": {},
      "extended_trailers": {},
      "web_url": "https://gitlab.com/stagepfa/test_1046_0806/-/commit/b5d9293a34705645fba661dba48f1d0ff479ec7c"
    },
    {
      "project_id": "72458495",
      "id": "53c27254c142dd7ab7a591da9e6ca1d15ca7118c",
      "short_id": "53c27254",
      "created_at": "2025-08-06T09:47:12.000+00:00",
      "parent_ids": [
        "dc9be75df4903498323dc03ada72755ed67db13f"
      ],
      "title": "Add new file",
      "message": "Add new file",
      "author_name": "Anas Akhssas",
      "author_email": "anasakhssas1@gmail.com",
      "authored_date": "2025-08-06T09:47:12.000+00:00",
      "committer_name": "Anas Akhssas",
      "committer_email": "anasakhssas1@gmail.com",
      "committed_date": "2025-08-06T09:47:12.000+00:00",
      "trailers": {},
      "extended_trailers": {},
      "web_url": "https://gitlab.com/stagepfa/test_1046_0806/-/commit/53c27254c142dd7ab7a591da9e6ca1d15ca7118c"
    },
    {
      "project_id": "72458495",
      "id": "dc9be75df4903498323dc03ada72755ed67db13f",
      "short_id": "dc9be75d",
      "created_at": "2025-08-06T09:46:44.000+00:00",
      "parent_ids": [],
      "title": "Initial commit",
      "message": "Initial commit",
      "author_name": "Anas Akhssas",
      "author_email": "anasakhssas1@gmail.com",
      "authored_date": "2025-08-06T09:46:44.000+00:00",
      "committer_name": "Anas Akhssas",
      "committer_email": "anasakhssas1@gmail.com",
      "committed_date": "2025-08-06T09:46:44.000+00:00",
      "trailers": {},
      "extended_trailers": {},
      "web_url": "https://gitlab.com/stagepfa/test_1046_0806/-/commit/dc9be75df4903498323dc03ada72755ed67db13f"
    }
  ],
  "72391249": [],
  "72390081": [],
  "72023033": [
    {
      "project_id": "72023033",
      "id": "68fc3a6a604f00a76816890d366434c31ab8d2bd",
      "short_id": "68fc3a6a",
      "created_at": "2025-08-06T13:06:03.000+00:00",
      "parent_ids": [
        "6801ab6fdef89daa9319f8db66a5a3a3dea383f6"
      ],
      "title": "Upload New File",
      "message": "Upload New File",
      "author_name": "salma eddib",
      "author_email": "salmaeddib03taza@gmail.com",
      "authored_date": "2025-08-06T13:06:03.000+00:00",
      "committer_name": "salma eddib",
      "committer_email": "salmaeddib03taza@gmail.com",
      "committed_date": "2025-08-06T13:06:03.000+00:00",
      "trailers": {},
      "extended_trailers": {},
      "web_url": "https://gitlab.com/stagepfa/devops_project/-/commit/68fc3a6a604f00a76816890d366434c31ab8d2bd"
    },
    {
      "project_id": "72023033",
      "id": "6801ab6fdef89daa9319f8db66a5a3a3dea383f6",
      "short_id": "6801ab6f",
      "created_at": "2025-08-06T12:19:07.000+01:00",
      "parent_ids": [],
      "title": "test for SQ",
      "message": "test for SQ\n",
      "author_name": "anasakhssas",
      "author_email": "anasakhssas357@gmail.com",
      "authored_date": "2025-08-06T12:19:07.000+01:00",
      "committer_name": "anasakhssas",
      "committer_email": "anasakhssas357@gmail.com",
      "committed_date": "2025-08-06T12:19:07.000+01:00",
      "trailers": {},
      "extended_trailers": {},
      "web_url": "https://gitlab.com/stagepfa/devops_project/-/commit/6801ab6fdef89daa9319f8db66a5a3a3dea383f6"
    }
  ],
  "71994072": [],
  "71906513": [],
  "71866675": [],
  "71825485": [],
  "71824847": [],
  "71824428": []
}