[
  {
    "id": 29317520,
    "username": "pelin-kilic_condor",
    "public_email": null,
    "name": "Kilic, Pelin",
    "state": "active",
    "locked": false,
    "avatar_url": "https://secure.gravatar.com/avatar/b3de736933c102761a92de94e5693c098a1fe883883cfc7e0c290835d95206fb?s=80&d=identicon",
    "web_url": "https://gitlab.com/pelin-kilic_condor"
  },
  {
    "id": 29317519,
    "username": "vv12347",
    "public_email": null,
    "name": "v v",
    "state": "active",
    "locked": false,
    "avatar_url": "https://secure.gravatar.com/avatar/d22f40b07a87c8ba6dcbee038fb1bd3156611040e320f9ddd8313b2341e7bb92?s=80&d=identicon",
    "web_url": "https://gitlab.com/vv12347"
  },
  {
    "id": 29317518,
    "username": "MithunDeegee",
    "public_email": null,
    "name": "Mithun Kumar",
    "state": "active",
    "locked": false,
    "avatar_url": "https://secure.gravatar.com/avatar/7e11da5fdec437d75ffbe5b61164cc0ae510dc6a9ddf017bf58235160a783d6f?s=80&d=identicon",
    "web_url": "https://gitlab.com/MithunDeegee"
  },
  {
    "id": 29317517,
    "username": "baokhang627228",
    "public_email": null,
    "name": "Baokhang",
    "state": "active",
    "locked": false,
    "avatar_url": "https://secure.gravatar.com/avatar/4dd2fc4540748f28181d2cafdc593cc2afae3f909d6b0ded04d372be52636567?s=80&d=identicon",
    "web_url": "https://gitlab.com/baokhang627228"
  },
  {
    "id": 29317516,
    "username": "danielsegal.ca",
    "public_email": null,
    "name": "Daniel Segal",
    "state": "active",
    "locked": false,
    "avatar_url": "https://secure.gravatar.com/avatar/a269440b387b82585f6f7b811b934bfb9cdea5d39e2140ce6676816924fdff22?s=80&d=identicon",
    "web_url": "https://gitlab.com/danielsegal.ca"
  },
  {
    "id": 29317515,
    "username": "mooreorganizations145",
    "public_email": null,
    "name": "Moore Organization",
    "state": "active",
    "locked": false,
    "avatar_url": "https://secure.gravatar.com/avatar/a1e42e0cdcd225263b13f83c1246b2c5a9fe910fc18b1e5005f680191acc311d?s=80&d=identicon",
    "web_url": "https://gitlab.com/mooreorganizations145"
  },
  {
    "id": 29317514,
    "username": "group_10233835_bot_978a20e78d8e1b9717277424411e2173",
    "public_email": null,
    "name": "****",
    "state": "active",
    "locked": false,
    "avatar_url": "https://secure.gravatar.com/avatar/3c58f64f53aa294ba414e1f84c85dadbbc0da6819ccfb7160e4664ef8f1b282b?s=80&d=identicon",
    "web_url": "https://gitlab.com/group_10233835_bot_978a20e78d8e1b9717277424411e2173"
  },
  {
    "id": 29317513,
    "username": "Ajabbark003",
    "public_email": null,
    "name": "Abdul Jabbar",
    "state": "active",
    "locked": false,
    "avatar_url": "https://secure.gravatar.com/avatar/10e8d35146969c211463d4b86d82f82aee7b1ec2fe682d07c2d2fe9c5999c755?s=80&d=identicon",
    "web_url": "https://gitlab.com/Ajabbark003"
  },
  {
    "id": 29317512,
    "username": "antoine.poirot",
    "public_email": null,
    "name": "Antoine Poirot",
    "state": "active",
    "locked": false,
    "avatar_url": "https://secure.gravatar.com/avatar/7dce908d677cacebfa6679fb93a46d81c8567cb0d8ffcaccba51073bcf467850?s=80&d=identicon",
    "web_url": "https://gitlab.com/antoine.poirot"
  },
  {
    "id": 29317511,
    "username": "tirangagame78",
    "public_email": null,
    "name": "Tiranga Game",
    "state": "active",
    "locked": false,
    "avatar_url": "https://secure.gravatar.com/avatar/05dafdbac79c679397b941719085a8dced13ec20124da685703f326c28cc35a4?s=80&d=identicon",
    "web_url": "https://gitlab.com/tirangagame78"
  },
  {
    "id": 29317510,
    "username": "may20250728",
    "public_email": null,
    "name": "tjsvab ejsnnf",
    "state": "active",
    "locked": false,
    "avatar_url": "https://secure.gravatar.com/avatar/89e0a64d0df7e34454525ec5192b84e4e6a50dd48697948b6bc2781c18560262?s=80&d=identicon",
    "web_url": "https://gitlab.com/may20250728"
  },
  {
    "id": 29317509,
    "username": "Jualo2k",
    "public_email": null,
    "name": "Juan Lo",
    "state": "active",
    "locked": false,
    "avatar_url": "https://secure.gravatar.com/avatar/65232f8d7ccaa2597647ab6c13e32e5de57b9d363ce6efa6006d709dd8478c12?s=80&d=identicon",
    "web_url": "https://gitlab.com/Jualo2k"
  },
  {
    "id": 29317508,
    "username": "mai7665fg",
    "public_email": null,
    "name": "Anh thư",
    "state": "active",
    "locked": false,
    "avatar_url": "https://secure.gravatar.com/avatar/5a202c8ac6002f4baa21cc312447405c3185a762b66284c02945f6a64776f62e?s=80&d=identicon",
    "web_url": "https://gitlab.com/mai7665fg"
  },
  {
    "id": 29317507,
    "username": "satyasuchak",
    "public_email": null,
    "name": "Satya Suchak",
    "state": "active",
    "locked": false,
    "avatar_url": "https://secure.gravatar.com/avatar/e697485a8b25023495bd0824387445680f0bd83012d90cb6e480dd690a8f0e6b?s=80&d=identicon",
    "web_url": "https://gitlab.com/satyasuchak"
  },
  {
    "id": 29317506,
    "username": "project_55976966_bot_f346c33033ab33f95d04026ba0c4030b",
    "public_email": null,
    "name": "****",
    "state": "active",
    "locked": false,
    "avatar_url": "https://secure.gravatar.com/avatar/4fb0ddafba39cface3ceddf80939d9c457cc82103713c09691310815ee7098f7?s=80&d=identicon",
    "web_url": "https://gitlab.com/project_55976966_bot_f346c33033ab33f95d04026ba0c4030b"
  },
  {
    "id": 29317505,
    "username": "kejinzha",
    "public_email": null,
    "name": "kejinzha",
    "state": "active",
    "locked": false,
    "avatar_url": "https://secure.gravatar.com/avatar/cbdc900f780aed909dfc6898519895194b9a276d21b498f2022b716c09f83c15?s=80&d=identicon",
    "web_url": "https://gitlab.com/kejinzha"
  },
  {
    "id": 29317504,
    "username": "project_66550175_bot_d34b3346a153bf7dc0f30f9af60c9d13",
    "public_email": null,
    "name": "****",
    "state": "active",
    "locked": false,
    "avatar_url": "https://secure.gravatar.com/avatar/5741a5fdc46d5579cd9543f0dde8ec0aebf66bad5c570689a62ddbce6c904d10?s=80&d=identicon",
    "web_url": "https://gitlab.com/project_66550175_bot_d34b3346a153bf7dc0f30f9af60c9d13"
  },
  {
    "id": 29317503,
    "username": "erza547",
    "public_email": null,
    "name": "sdsdf ads",
    "state": "active",
    "locked": false,
    "avatar_url": "https://secure.gravatar.com/avatar/a1a309d8527e71085f66595aac6b88cd4debd4251a82f0560182f9fe730854e9?s=80&d=identicon",
    "web_url": "https://gitlab.com/erza547"
  },
  {
    "id": 29317502,
    "username": "project_72018225_bot_b58bddac83892826936c57a64aba07a4",
    "public_email": null,
    "name": "****",
    "state": "active",
    "locked": false,
    "avatar_url": "https://secure.gravatar.com/avatar/ad933510cd6c7a6878959069e0f2c87bae8da55d72b33cf8c580f6fea7807cb2?s=80&d=identicon",
    "web_url": "https://gitlab.com/project_72018225_bot_b58bddac83892826936c57a64aba07a4"
  },
  {
    "id": 29317501,
    "username": "project_50950678_bot_57f6753a276001814f0bdd6f77f0b138",
    "public_email": null,
    "name": "****",
    "state": "active",
    "locked": false,
    "avatar_url": "https://secure.gravatar.com/avatar/b73d0ba0f83192d44f03c79ffc082ea6f7cbaa2b10f20eb17a7f4376be9b5c13?s=80&d=identicon",
    "web_url": "https://gitlab.com/project_50950678_bot_57f6753a276001814f0bdd6f77f0b138"
  }
]